busbus-0.1.0.dist-info/RECORD
busbus-0.1.0.dist-info/WHEEL
busbus-0.1.0.dist-info/metadata.json
busbus-0.1.0.dist-info/DESCRIPTION.rst
busbus-0.1.0.dist-info/METADATA
busbus-0.1.0.dist-info/top_level.txt
busbus/web.py
busbus/queryable.py
busbus/entity.py
busbus/__init__.py
busbus/util/csv.py
busbus/util/arrivals.py
busbus/util/__init__.py
busbus/provider/mbta.py
busbus/provider/lawrenceks.py
busbus/provider/gtfs.py
busbus/provider/ctran.py
busbus/provider/__init__.py
busbus/provider/gtfs_2015020201.sql
