Metadata-Version: 2.0
Name: busbus
Version: 0.1.0
Summary: A platform for working with public transit data
Home-page: https://github.com/spaceboats/busbus
Author: Ian Weller
Author-email: ianweller@buttslol.net
License: MIT
Platform: UNKNOWN
Requires-Dist: six
Requires-Dist: requests[security]
Requires-Dist: CacheControl (>=0.10.8)
Requires-Dist: lockfile
Requires-Dist: phonenumbers
Requires-Dist: arrow
Requires-Dist: apsw
Requires-Dist: setuptools
Provides-Extra: dev
Requires-Dist: pytest-pep8; extra == 'dev'
Requires-Dist: pytest-cache; extra == 'dev'
Requires-Dist: pytest; extra == 'dev'
Requires-Dist: wsgi-intercept; extra == 'dev'
Requires-Dist: mock; extra == 'dev'
Requires-Dist: responses; extra == 'dev'
Requires-Dist: httpbin; extra == 'dev'
Requires-Dist: wheel; extra == 'dev'
Provides-Extra: web
Requires-Dist: CherryPy; extra == 'web'
